{
	"format_version": "1.12.0",
	"minecraft:geometry": [
		{
			"description": {
				"identifier": "geometry.shulker_wall",
				"texture_width": 64,
				"texture_height": 64,
				"visible_bounds_width": 4,
				"visible_bounds_height": 4.5,
				"visible_bounds_offset": [0, 1.75, 0]
			},
			"bones": [
				{
					"name": "head",
					"pivot": [0, 8, 8],
					"rotation": [90, 0, 0],
					"cubes": [
						{"origin": [-3, 14, 5], "size": [6, 6, 6], "uv": [0, 52]},
						{
							"origin": [-7.775, 8, 0.1],
							"size": [15.575, 8, 15.775],
							"uv": {
								"north": {"uv": [16, 44], "uv_size": [16, 8]},
								"east": {"uv": [0, 44], "uv_size": [16, 8]},
								"south": {"uv": [48, 44], "uv_size": [16, 8]},
								"west": {"uv": [32, 44], "uv_size": [16, 8]},
								"up": {"uv": [16, 28], "uv_size": [16, 16]},
								"down": {"uv": [32, 44], "uv_size": [16, -16]}
							}
						}
					]
				}
			]
		}
	]
}