{
	"format_version": "1.12.0",
	"minecraft:geometry": [
		{
			"description": {
				"identifier": "geometry.ghast_mask",
				"texture_width": 64,
				"texture_height": 64,
				"visible_bounds_width": 3,
				"visible_bounds_height": 3,
				"visible_bounds_offset": [0, 1.5, 0]
			},
			"bones": [
				{
					"name": "head",
					"pivot": [0, 24, 0],
					"cubes": [
						{
							"origin": [-4, 24, -4],
							"size": [8, 8, 8],
							"inflate": 0.5,
							"uv": {
								"north": {"uv": [17, 34], "uv_size": [15, 30]},
								"east": {"uv": [0, 32], "uv_size": [17, 32]},
								"south": {"uv": [49, 32], "uv_size": [15, 32]},
								"west": {"uv": [33, 32], "uv_size": [14, 32]},
								"up": {"uv": [16, 0], "uv_size": [16, 32]},
								"down": {"uv": [33, 32], "uv_size": [15, -32]}
							}
						},
						{
							"origin": [-7.9, 23.5, -3.25],
							"size": [3.425, 1, 1],
							"uv": {
								"north": {"uv": [0, 4], "uv_size": [8.125, 27.7]},
								"east": {"uv": [0, 4], "uv_size": [8.125, 27.7]},
								"south": {"uv": [0, 4], "uv_size": [8.125, 27.7]},
								"west": {"uv": [0, 4], "uv_size": [8.125, 27.7]},
								"up": {"uv": [8.125, 31.7], "uv_size": [-8.125, -27.7]},
								"down": {"uv": [8.125, 31.7], "uv_size": [-8.125, -27.7]}
							}
						},
						{
							"origin": [-7.9, 23.5, -0.425],
							"size": [3.425, 1, 1],
							"uv": {
								"north": {"uv": [0, 4], "uv_size": [8.125, 27.7]},
								"east": {"uv": [0, 4], "uv_size": [8.125, 27.7]},
								"south": {"uv": [0, 4], "uv_size": [8.125, 27.7]},
								"west": {"uv": [0, 4], "uv_size": [8.125, 27.7]},
								"up": {"uv": [8.125, 31.7], "uv_size": [-8.125, -27.7]},
								"down": {"uv": [8.125, 31.7], "uv_size": [-8.125, -27.7]}
							}
						},
						{
							"origin": [-7.9, 23.5, 2.475],
							"size": [3.425, 1, 1],
							"uv": {
								"north": {"uv": [0, 4], "uv_size": [8.125, 27.7]},
								"east": {"uv": [0, 4], "uv_size": [8.125, 27.7]},
								"south": {"uv": [0, 4], "uv_size": [8.125, 27.7]},
								"west": {"uv": [0, 4], "uv_size": [8.125, 27.7]},
								"up": {"uv": [8.125, 31.7], "uv_size": [-8.125, -27.7]},
								"down": {"uv": [8.125, 31.7], "uv_size": [-8.125, -27.7]}
							}
						},
						{
							"origin": [4.35, 23.5, -0.425],
							"size": [3.425, 1, 1],
							"uv": {
								"north": {"uv": [0, 4], "uv_size": [8.125, 27.7]},
								"east": {"uv": [0, 4], "uv_size": [8.125, 27.7]},
								"south": {"uv": [0, 4], "uv_size": [8.125, 27.7]},
								"west": {"uv": [0, 4], "uv_size": [8.125, 27.7]},
								"up": {"uv": [8.125, 31.7], "uv_size": [-8.125, -27.7]},
								"down": {"uv": [8.125, 31.7], "uv_size": [-8.125, -27.7]}
							}
						},
						{
							"origin": [4.375, 23.5, 2.475],
							"size": [3.425, 1, 1],
							"uv": {
								"north": {"uv": [0, 4], "uv_size": [8.125, 27.7]},
								"east": {"uv": [0, 4], "uv_size": [8.125, 27.7]},
								"south": {"uv": [0, 4], "uv_size": [8.125, 27.7]},
								"west": {"uv": [0, 4], "uv_size": [8.125, 27.7]},
								"up": {"uv": [8.125, 31.7], "uv_size": [-8.125, -27.7]},
								"down": {"uv": [8.125, 31.7], "uv_size": [-8.125, -27.7]}
							}
						},
						{
							"origin": [4.25, 23.5, -3.25],
							"size": [3.425, 1, 1],
							"uv": {
								"north": {"uv": [0, 4], "uv_size": [8.125, 27.7]},
								"east": {"uv": [0, 4], "uv_size": [8.125, 27.7]},
								"south": {"uv": [0, 4], "uv_size": [8.125, 27.7]},
								"west": {"uv": [0, 4], "uv_size": [8.125, 27.7]},
								"up": {"uv": [8.125, 31.7], "uv_size": [-8.125, -27.7]},
								"down": {"uv": [8.125, 31.7], "uv_size": [-8.125, -27.7]}
							}
						}
					],
					"locators": {
						"locator": [0, 28, 0]
					}
				}
			]
		}
	]
}